{
    "file": "videoplayback.mp4",
    "duration_sec": 68.22,
    "windows_analyzed": 69,
    "temporal_pulse": [
        {
            "window_start_sec": 0,
            "window_end_sec": 1,
            "rms_energy": 0.0345,
            "spectral_centroid": 638.77,
            "spectral_flux": 10.0084,
            "rms_delta_pct": 0.0,
            "centroid_delta_pct": 0.0
        },
        {
            "window_start_sec": 1,
            "window_end_sec": 2,
            "rms_energy": 0.0937,
            "spectral_centroid": 1544.45,
            "spectral_flux": 36.9112,
            "rms_delta_pct": 171.59,
            "centroid_delta_pct": 141.78
        },
        {
            "window_start_sec": 2,
            "window_end_sec": 3,
            "rms_energy": 0.0993,
            "spectral_centroid": 1968.04,
            "spectral_flux": 37.3466,
            "rms_delta_pct": 5.98,
            "centroid_delta_pct": 27.43
        },
        {
            "window_start_sec": 3,
            "window_end_sec": 4,
            "rms_energy": 0.1148,
            "spectral_centroid": 2325.02,
            "spectral_flux": 41.781,
            "rms_delta_pct": 15.61,
            "centroid_delta_pct": 18.14
        },
        {
            "window_start_sec": 4,
            "window_end_sec": 5,
            "rms_energy": 0.0621,
            "spectral_centroid": 1787.09,
            "spectral_flux": 14.4199,
            "rms_delta_pct": -45.91,
            "centroid_delta_pct": -23.14
        },
        {
            "window_start_sec": 5,
            "window_end_sec": 6,
            "rms_energy": 0.033,
            "spectral_centroid": 1016.17,
            "spectral_flux": 6.5432,
            "rms_delta_pct": -46.86,
            "centroid_delta_pct": -43.14
        },
        {
            "window_start_sec": 6,
            "window_end_sec": 7,
            "rms_energy": 0.0233,
            "spectral_centroid": 1311.19,
            "spectral_flux": 6.6033,
            "rms_delta_pct": -29.39,
            "centroid_delta_pct": 29.03
        },
        {
            "window_start_sec": 7,
            "window_end_sec": 8,
            "rms_energy": 0.087,
            "spectral_centroid": 2378.32,
            "spectral_flux": 35.1829,
            "rms_delta_pct": 273.39,
            "centroid_delta_pct": 81.39
        },
        {
            "window_start_sec": 8,
            "window_end_sec": 9,
            "rms_energy": 0.0495,
            "spectral_centroid": 1240.13,
            "spectral_flux": 14.4981,
            "rms_delta_pct": -43.1,
            "centroid_delta_pct": -47.86
        },
        {
            "window_start_sec": 9,
            "window_end_sec": 10,
            "rms_energy": 0.0332,
            "spectral_centroid": 1139.55,
            "spectral_flux": 8.0509,
            "rms_delta_pct": -32.93,
            "centroid_delta_pct": -8.11
        },
        {
            "window_start_sec": 10,
            "window_end_sec": 11,
            "rms_energy": 0.0523,
            "spectral_centroid": 1106.42,
            "spectral_flux": 6.5198,
            "rms_delta_pct": 57.53,
            "centroid_delta_pct": -2.91
        },
        {
            "window_start_sec": 11,
            "window_end_sec": 12,
            "rms_energy": 0.0515,
            "spectral_centroid": 1285.85,
            "spectral_flux": 8.1719,
            "rms_delta_pct": -1.53,
            "centroid_delta_pct": 16.22
        },
        {
            "window_start_sec": 12,
            "window_end_sec": 13,
            "rms_energy": 0.0403,
            "spectral_centroid": 1736.34,
            "spectral_flux": 11.3757,
            "rms_delta_pct": -21.75,
            "centroid_delta_pct": 35.03
        },
        {
            "window_start_sec": 13,
            "window_end_sec": 14,
            "rms_energy": 0.043,
            "spectral_centroid": 1697.15,
            "spectral_flux": 11.8132,
            "rms_delta_pct": 6.7,
            "centroid_delta_pct": -2.26
        },
        {
            "window_start_sec": 14,
            "window_end_sec": 15,
            "rms_energy": 0.0243,
            "spectral_centroid": 1668.62,
            "spectral_flux": 6.3713,
            "rms_delta_pct": -43.49,
            "centroid_delta_pct": -1.68
        },
        {
            "window_start_sec": 15,
            "window_end_sec": 16,
            "rms_energy": 0.0233,
            "spectral_centroid": 2012.06,
            "spectral_flux": 5.16,
            "rms_delta_pct": -4.12,
            "centroid_delta_pct": 20.58
        },
        {
            "window_start_sec": 16,
            "window_end_sec": 17,
            "rms_energy": 0.0751,
            "spectral_centroid": 1811.47,
            "spectral_flux": 22.823,
            "rms_delta_pct": 222.32,
            "centroid_delta_pct": -9.97
        },
        {
            "window_start_sec": 17,
            "window_end_sec": 18,
            "rms_energy": 0.079,
            "spectral_centroid": 2840.97,
            "spectral_flux": 28.9189,
            "rms_delta_pct": 5.19,
            "centroid_delta_pct": 56.83
        },
        {
            "window_start_sec": 18,
            "window_end_sec": 19,
            "rms_energy": 0.0713,
            "spectral_centroid": 2549.44,
            "spectral_flux": 27.0236,
            "rms_delta_pct": -9.75,
            "centroid_delta_pct": -10.26
        },
        {
            "window_start_sec": 19,
            "window_end_sec": 20,
            "rms_energy": 0.0313,
            "spectral_centroid": 1272.56,
            "spectral_flux": 10.8209,
            "rms_delta_pct": -56.1,
            "centroid_delta_pct": -50.08
        },
        {
            "window_start_sec": 20,
            "window_end_sec": 21,
            "rms_energy": 0.0295,
            "spectral_centroid": 1257.37,
            "spectral_flux": 9.1005,
            "rms_delta_pct": -5.75,
            "centroid_delta_pct": -1.19
        },
        {
            "window_start_sec": 21,
            "window_end_sec": 22,
            "rms_energy": 0.0584,
            "spectral_centroid": 1804.06,
            "spectral_flux": 21.1146,
            "rms_delta_pct": 97.97,
            "centroid_delta_pct": 43.48
        },
        {
            "window_start_sec": 22,
            "window_end_sec": 23,
            "rms_energy": 0.091,
            "spectral_centroid": 1389.02,
            "spectral_flux": 28.4572,
            "rms_delta_pct": 55.82,
            "centroid_delta_pct": -23.01
        },
        {
            "window_start_sec": 23,
            "window_end_sec": 24,
            "rms_energy": 0.0793,
            "spectral_centroid": 1111.81,
            "spectral_flux": 25.1654,
            "rms_delta_pct": -12.86,
            "centroid_delta_pct": -19.96
        },
        {
            "window_start_sec": 24,
            "window_end_sec": 25,
            "rms_energy": 0.0915,
            "spectral_centroid": 1190.28,
            "spectral_flux": 25.8504,
            "rms_delta_pct": 15.38,
            "centroid_delta_pct": 7.06
        },
        {
            "window_start_sec": 25,
            "window_end_sec": 26,
            "rms_energy": 0.1551,
            "spectral_centroid": 1097.79,
            "spectral_flux": 42.6035,
            "rms_delta_pct": 69.51,
            "centroid_delta_pct": -7.77
        },
        {
            "window_start_sec": 26,
            "window_end_sec": 27,
            "rms_energy": 0.1125,
            "spectral_centroid": 1344.42,
            "spectral_flux": 35.7563,
            "rms_delta_pct": -27.47,
            "centroid_delta_pct": 22.47
        },
        {
            "window_start_sec": 27,
            "window_end_sec": 28,
            "rms_energy": 0.0712,
            "spectral_centroid": 1324.34,
            "spectral_flux": 23.3011,
            "rms_delta_pct": -36.71,
            "centroid_delta_pct": -1.49
        },
        {
            "window_start_sec": 28,
            "window_end_sec": 29,
            "rms_energy": 0.0883,
            "spectral_centroid": 1545.45,
            "spectral_flux": 30.6865,
            "rms_delta_pct": 24.02,
            "centroid_delta_pct": 16.7
        },
        {
            "window_start_sec": 29,
            "window_end_sec": 30,
            "rms_energy": 0.0863,
            "spectral_centroid": 1231.9,
            "spectral_flux": 30.2472,
            "rms_delta_pct": -2.27,
            "centroid_delta_pct": -20.29
        },
        {
            "window_start_sec": 30,
            "window_end_sec": 31,
            "rms_energy": 0.0524,
            "spectral_centroid": 1373.79,
            "spectral_flux": 18.2821,
            "rms_delta_pct": -39.28,
            "centroid_delta_pct": 11.52
        },
        {
            "window_start_sec": 31,
            "window_end_sec": 32,
            "rms_energy": 0.0636,
            "spectral_centroid": 1718.72,
            "spectral_flux": 23.8069,
            "rms_delta_pct": 21.37,
            "centroid_delta_pct": 25.11
        },
        {
            "window_start_sec": 32,
            "window_end_sec": 33,
            "rms_energy": 0.0802,
            "spectral_centroid": 1605.67,
            "spectral_flux": 28.6041,
            "rms_delta_pct": 26.1,
            "centroid_delta_pct": -6.58
        },
        {
            "window_start_sec": 33,
            "window_end_sec": 34,
            "rms_energy": 0.0843,
            "spectral_centroid": 1382.97,
            "spectral_flux": 31.4147,
            "rms_delta_pct": 5.11,
            "centroid_delta_pct": -13.87
        },
        {
            "window_start_sec": 34,
            "window_end_sec": 35,
            "rms_energy": 0.1483,
            "spectral_centroid": 2226.05,
            "spectral_flux": 49.7444,
            "rms_delta_pct": 75.92,
            "centroid_delta_pct": 60.96
        },
        {
            "window_start_sec": 35,
            "window_end_sec": 36,
            "rms_energy": 0.0699,
            "spectral_centroid": 3290.19,
            "spectral_flux": 28.7545,
            "rms_delta_pct": -52.87,
            "centroid_delta_pct": 47.8
        },
        {
            "window_start_sec": 36,
            "window_end_sec": 37,
            "rms_energy": 0.0596,
            "spectral_centroid": 2981.52,
            "spectral_flux": 23.5158,
            "rms_delta_pct": -14.74,
            "centroid_delta_pct": -9.38
        },
        {
            "window_start_sec": 37,
            "window_end_sec": 38,
            "rms_energy": 0.0982,
            "spectral_centroid": 2691.56,
            "spectral_flux": 37.6626,
            "rms_delta_pct": 64.77,
            "centroid_delta_pct": -9.73
        },
        {
            "window_start_sec": 38,
            "window_end_sec": 39,
            "rms_energy": 0.1541,
            "spectral_centroid": 3787.39,
            "spectral_flux": 65.1121,
            "rms_delta_pct": 56.92,
            "centroid_delta_pct": 40.71
        },
        {
            "window_start_sec": 39,
            "window_end_sec": 40,
            "rms_energy": 0.0919,
            "spectral_centroid": 2802.61,
            "spectral_flux": 36.8646,
            "rms_delta_pct": -40.36,
            "centroid_delta_pct": -26.0
        },
        {
            "window_start_sec": 40,
            "window_end_sec": 41,
            "rms_energy": 0.0807,
            "spectral_centroid": 486.56,
            "spectral_flux": 20.9778,
            "rms_delta_pct": -12.19,
            "centroid_delta_pct": -82.64
        },
        {
            "window_start_sec": 41,
            "window_end_sec": 42,
            "rms_energy": 0.1623,
            "spectral_centroid": 2233.24,
            "spectral_flux": 58.3658,
            "rms_delta_pct": 101.12,
            "centroid_delta_pct": 358.99
        },
        {
            "window_start_sec": 42,
            "window_end_sec": 43,
            "rms_energy": 0.1358,
            "spectral_centroid": 1938.34,
            "spectral_flux": 48.6453,
            "rms_delta_pct": -16.33,
            "centroid_delta_pct": -13.21
        },
        {
            "window_start_sec": 43,
            "window_end_sec": 44,
            "rms_energy": 0.163,
            "spectral_centroid": 2143.14,
            "spectral_flux": 60.3618,
            "rms_delta_pct": 20.03,
            "centroid_delta_pct": 10.57
        },
        {
            "window_start_sec": 44,
            "window_end_sec": 45,
            "rms_energy": 0.151,
            "spectral_centroid": 2654.39,
            "spectral_flux": 50.8912,
            "rms_delta_pct": -7.36,
            "centroid_delta_pct": 23.86
        },
        {
            "window_start_sec": 45,
            "window_end_sec": 46,
            "rms_energy": 0.1285,
            "spectral_centroid": 2338.16,
            "spectral_flux": 48.6245,
            "rms_delta_pct": -14.9,
            "centroid_delta_pct": -11.91
        },
        {
            "window_start_sec": 46,
            "window_end_sec": 47,
            "rms_energy": 0.1116,
            "spectral_centroid": 1853.66,
            "spectral_flux": 35.0406,
            "rms_delta_pct": -13.15,
            "centroid_delta_pct": -20.72
        },
        {
            "window_start_sec": 47,
            "window_end_sec": 48,
            "rms_energy": 0.1219,
            "spectral_centroid": 1988.93,
            "spectral_flux": 41.3113,
            "rms_delta_pct": 9.23,
            "centroid_delta_pct": 7.3
        },
        {
            "window_start_sec": 48,
            "window_end_sec": 49,
            "rms_energy": 0.108,
            "spectral_centroid": 1869.08,
            "spectral_flux": 38.6502,
            "rms_delta_pct": -11.4,
            "centroid_delta_pct": -6.03
        },
        {
            "window_start_sec": 49,
            "window_end_sec": 50,
            "rms_energy": 0.1405,
            "spectral_centroid": 2689.76,
            "spectral_flux": 52.5957,
            "rms_delta_pct": 30.09,
            "centroid_delta_pct": 43.91
        },
        {
            "window_start_sec": 50,
            "window_end_sec": 51,
            "rms_energy": 0.1492,
            "spectral_centroid": 2732.7,
            "spectral_flux": 51.2193,
            "rms_delta_pct": 6.19,
            "centroid_delta_pct": 1.6
        },
        {
            "window_start_sec": 51,
            "window_end_sec": 52,
            "rms_energy": 0.1226,
            "spectral_centroid": 2024.35,
            "spectral_flux": 41.0813,
            "rms_delta_pct": -17.83,
            "centroid_delta_pct": -25.92
        },
        {
            "window_start_sec": 52,
            "window_end_sec": 53,
            "rms_energy": 0.1197,
            "spectral_centroid": 1864.23,
            "spectral_flux": 44.3311,
            "rms_delta_pct": -2.37,
            "centroid_delta_pct": -7.91
        },
        {
            "window_start_sec": 53,
            "window_end_sec": 54,
            "rms_energy": 0.1016,
            "spectral_centroid": 2542.78,
            "spectral_flux": 39.3377,
            "rms_delta_pct": -15.12,
            "centroid_delta_pct": 36.4
        },
        {
            "window_start_sec": 54,
            "window_end_sec": 55,
            "rms_energy": 0.1401,
            "spectral_centroid": 2740.67,
            "spectral_flux": 49.5324,
            "rms_delta_pct": 37.89,
            "centroid_delta_pct": 7.78
        },
        {
            "window_start_sec": 55,
            "window_end_sec": 56,
            "rms_energy": 0.1242,
            "spectral_centroid": 2941.0,
            "spectral_flux": 50.8474,
            "rms_delta_pct": -11.35,
            "centroid_delta_pct": 7.31
        },
        {
            "window_start_sec": 56,
            "window_end_sec": 57,
            "rms_energy": 0.1167,
            "spectral_centroid": 2545.12,
            "spectral_flux": 46.8796,
            "rms_delta_pct": -6.04,
            "centroid_delta_pct": -13.46
        },
        {
            "window_start_sec": 57,
            "window_end_sec": 58,
            "rms_energy": 0.1201,
            "spectral_centroid": 3747.83,
            "spectral_flux": 55.1423,
            "rms_delta_pct": 2.91,
            "centroid_delta_pct": 47.26
        },
        {
            "window_start_sec": 58,
            "window_end_sec": 59,
            "rms_energy": 0.0944,
            "spectral_centroid": 2431.95,
            "spectral_flux": 25.4222,
            "rms_delta_pct": -21.4,
            "centroid_delta_pct": -35.11
        },
        {
            "window_start_sec": 59,
            "window_end_sec": 60,
            "rms_energy": 0.0692,
            "spectral_centroid": 661.6,
            "spectral_flux": 4.5517,
            "rms_delta_pct": -26.69,
            "centroid_delta_pct": -72.8
        },
        {
            "window_start_sec": 60,
            "window_end_sec": 61,
            "rms_energy": 0.0689,
            "spectral_centroid": 168.87,
            "spectral_flux": 13.3664,
            "rms_delta_pct": -0.43,
            "centroid_delta_pct": -74.48
        },
        {
            "window_start_sec": 61,
            "window_end_sec": 62,
            "rms_energy": 0.0246,
            "spectral_centroid": 898.11,
            "spectral_flux": 11.6832,
            "rms_delta_pct": -64.3,
            "centroid_delta_pct": 431.84
        },
        {
            "window_start_sec": 62,
            "window_end_sec": 63,
            "rms_energy": 0.0656,
            "spectral_centroid": 962.24,
            "spectral_flux": 21.6703,
            "rms_delta_pct": 166.67,
            "centroid_delta_pct": 7.14
        },
        {
            "window_start_sec": 63,
            "window_end_sec": 64,
            "rms_energy": 0.0526,
            "spectral_centroid": 849.85,
            "spectral_flux": 17.8659,
            "rms_delta_pct": -19.82,
            "centroid_delta_pct": -11.68
        },
        {
            "window_start_sec": 64,
            "window_end_sec": 65,
            "rms_energy": 0.033,
            "spectral_centroid": 560.65,
            "spectral_flux": 10.8283,
            "rms_delta_pct": -37.26,
            "centroid_delta_pct": -34.03
        },
        {
            "window_start_sec": 65,
            "window_end_sec": 66,
            "rms_energy": 0.0136,
            "spectral_centroid": 647.8,
            "spectral_flux": 4.3517,
            "rms_delta_pct": -58.79,
            "centroid_delta_pct": 15.54
        },
        {
            "window_start_sec": 66,
            "window_end_sec": 67,
            "rms_energy": 0.0053,
            "spectral_centroid": 1000.6,
            "spectral_flux": 1.4682,
            "rms_delta_pct": -61.03,
            "centroid_delta_pct": 54.46
        },
        {
            "window_start_sec": 67,
            "window_end_sec": 68,
            "rms_energy": 0.001,
            "spectral_centroid": 1608.44,
            "spectral_flux": 0.2862,
            "rms_delta_pct": -81.13,
            "centroid_delta_pct": 60.75
        },
        {
            "window_start_sec": 68,
            "window_end_sec": 69,
            "rms_energy": 0.0,
            "spectral_centroid": 4481.27,
            "spectral_flux": 0.0131,
            "rms_delta_pct": -100.0,
            "centroid_delta_pct": 178.61
        }
    ]
}